AUTHORS
ChangeLog
LICENSE
README.md
example.py
requirements.txt
setup.cfg
setup.py
.pytest_cache/README.md
.pytest_cache/v/cache/nodeids
simpleconf2/__init__.py
simpleconf2/exceptions.py
simpleconf2/filename.py
simpleconf2/option.py
simpleconf2/section.py
simpleconf2/validators.py
simpleconf2.egg-info/PKG-INFO
simpleconf2.egg-info/SOURCES.txt
simpleconf2.egg-info/dependency_links.txt
simpleconf2.egg-info/not-zip-safe
simpleconf2.egg-info/pbr.json
simpleconf2.egg-info/requires.txt
simpleconf2.egg-info/top_level.txt
simpleconf2/dialogs/wx.py
tests/__init__.py
tests/exception_test.py
tests/filename_test.py
tests/option_test.py
tests/section_test.py
tests/validation_test.py